mediawiki/__init__.py
mediawiki/version.py
mediawiki/wiki.py
mediawiki/doc/generate_syntax_demo.py
mediawiki/wikimarkup/__init__.py
mediawiki2html-0.0.3.dist-info/AUTHORS
mediawiki2html-0.0.3.dist-info/COPYING
mediawiki2html-0.0.3.dist-info/METADATA
mediawiki2html-0.0.3.dist-info/WHEEL
mediawiki2html-0.0.3.dist-info/top_level.txt
mediawiki2html-0.0.3.dist-info/RECORD
