Metadata-Version: 2.1
Name: mediawiki2html
Version: 0.0.3
Summary: MediaWiki Syntax to HTML
Home-page: https://github.com/brondsem/mediawiki2html
Author: Raimon Esteve
Author-email: zikzak@zikzakmedia.com
License: GPLv3+
Platform: a
Platform: n
Platform: y
Classifier: Development Status :: 4 - Beta
Classifier: Environment :: Web Environment
Classifier: Intended Audience :: Developers
Classifier: License :: OSI Approved :: GNU General Public License (GPL)
Classifier: Operating System :: OS Independent
Classifier: Programming Language :: Python
Classifier: Programming Language :: Python :: 3
Classifier: Topic :: Internet :: WWW/HTTP :: Dynamic Content
Classifier: Topic :: Software Development :: Libraries :: Python Modules
Requires-Dist: six
